wttr.py
wttr-0.5.1.data/scripts/wttr
wttr-0.5.1.data/scripts/wttr.py
wttr-0.5.1.dist-info/METADATA
wttr-0.5.1.dist-info/WHEEL
wttr-0.5.1.dist-info/top_level.txt
wttr-0.5.1.dist-info/RECORD
