Metadata-Version: 2.1
Name: wttr
Version: 0.5.1
Summary: wttr.in wrapper for cli
Home-page: https://github.com/mendelmaleh/wttr.py
Author: Mendel E.
License: UNKNOWN
Platform: UNKNOWN
Requires-Dist: httpx
Requires-Dist: docopt
